{
  "category": "Set de Elya Wood (Categoría : Amuleto)",
  "full_name": "Talismán de Elya Wood (Niv. 135)",
  "level": "Niv.135",
  "name": "Talismán de Elya Wood",
  "pods": "10 pods",
  "price_beta": "Precio/unidad : 45.600",
  "recipe:1": "x70 - Piedra de topacio",
  "recipe:2": "x10 - Piedra de diamante",
  "recipe:3": "x10 - Piedra de zafiro",
  "recipe:4": "x10 - Pólvora de Aniripsa",
  "recipe:5": "",
  "recipe:6": "x2 - Tejido de Maho Firefux",
  "recipe:7": "x2 - Esmeralda",
  "recipe:8": "x1 - Pelos de MOON"
}