{
  "category": "Categoría : Cinturón",
  "full_name": "Cinturón del Temblador Regordete (Niv. 55)",
  "level": "Niv.55",
  "name": "Cinturón del Temblador Regordete",
  "pods": "8 pods",
  "price_beta": "Precio/unidad : 8.000",
  "recipe:1": "x12 - Cuero de Jabalí",
  "recipe:2": "x10 - Cuero de jabalí de las llanuras",
  "recipe:3": "x10 - Cuero del cochinil",
  "recipe:4": "x4 - Cuero del jefe de guerra jalató",
  "recipe:5": "x4 - Escama de cocodrail",
  "recipe:6": "x? - Escama de jefe cocodrail",
  "recipe:7": "",
  "recipe:8": ""
}